mosaic_env/__init__.py
mosaic_env-1.9.0.dist-info/METADATA
mosaic_env-1.9.0.dist-info/WHEEL
mosaic_env-1.9.0.dist-info/RECORD
