Metadata-Version: 2.1
Name: mosaic-env
Version: 1.9.0
Summary: MOSAIC environment command line utility (mosaic_env)
License: Apache-2.0
Keywords: ANAGEN,MOSAIC
Author: AnaGen Development Team
Requires-Python: >=3.11
Classifier: Development Status :: 4 - Beta
Classifier: License :: OSI Approved :: Apache Software License
Classifier: Operating System :: POSIX :: Linux
Classifier: Programming Language :: Python :: 3
Classifier: Programming Language :: Python :: 3.11
Classifier: Programming Language :: Python :: 3.12
Classifier: Topic :: Scientific/Engineering :: Electronic Design Automation (EDA)
Requires-Dist: GitPython (>=3.1.31,<4.0.0)
Requires-Dist: black (>=23.1.0,<24.0.0)
Requires-Dist: cookiecutter
Requires-Dist: esbonio (>=0.16.1,<0.17.0)
Requires-Dist: mosaic-orchestrator (==2.1.0)
Requires-Dist: mosaic-orchestrator-ui (==0.3.0)
Requires-Dist: numpy (>=1.24.2,<2.0.0)
Requires-Dist: pluggy (>=1.3.0,<2.0.0)
Requires-Dist: rich (>=13.3.1,<14.0.0)
Requires-Dist: semantic_version
Requires-Dist: toml (>=0.10.2,<0.11.0)
Requires-Dist: tox
Requires-Dist: typer (>=0.9.0,<0.10.0)
Requires-Dist: wheel_inspect (>=1.7.1,<2.0.0)
